artifactor/__init__.py
artifactor/__main__.py
artifactor/cli.py
artifactor/fetch.py
artifactor/generator.py
artifactor/ingest.py
artifactor/models.py
artifactor/config/__init__.py
artifactor/config/loader.py
artifactor/config/schema.py
artifactor/sources/__init__.py
artifactor/sources/base.py
artifactor/sources/generic.py
artifactor/sources/registry.py
artifactor/sources/socket_blog.py
artifactor-0.2.1.dist-info/licenses/LICENSE
artifactor-0.2.1.dist-info/METADATA
artifactor-0.2.1.dist-info/WHEEL
artifactor-0.2.1.dist-info/entry_points.txt
artifactor-0.2.1.dist-info/top_level.txt
artifactor-0.2.1.dist-info/RECORD
