Metadata-Version: 2.4
Name: artifactor
Version: 0.2.1
Summary: Deterministic CLI that ingests article URLs/HTML and emits Jekyll-ready posts
Project-URL: Repository, https://github.com/K-reel/artifactor
Keywords: jekyll,blog,cli,deterministic,content-ingestion
Classifier: Development Status :: 3 - Alpha
Classifier: Intended Audience :: Developers
Classifier: License :: OSI Approved :: MIT License
Classifier: Programming Language :: Python :: 3
Classifier: Programming Language :: Python :: 3.10
Classifier: Programming Language :: Python :: 3.11
Classifier: Programming Language :: Python :: 3.12
Classifier: Operating System :: OS Independent
Requires-Python: >=3.10
License-File: LICENSE
Requires-Dist: typer>=0.9.0
Requires-Dist: typing-extensions>=4.0.0
Requires-Dist: jinja2>=3.1.0
Requires-Dist: pyyaml>=6.0
Requires-Dist: httpx>=0.27.0
Requires-Dist: beautifulsoup4>=4.12.0
Requires-Dist: python-dateutil>=2.8.0
Provides-Extra: dev
Requires-Dist: pytest>=7.0.0; extra == "dev"
Requires-Dist: build>=1.0.0; extra == "dev"
Requires-Dist: twine>=4.0.0; extra == "dev"
Dynamic: license-file
